renamify/__init__.py
renamify/__main__.py
renamify/core.py
renamify-1.0.1.dist-info/LICENSE
renamify-1.0.1.dist-info/METADATA
renamify-1.0.1.dist-info/WHEEL
renamify-1.0.1.dist-info/top_level.txt
renamify-1.0.1.dist-info/RECORD
